environment_provider/__init__.py
environment_provider/environment.py
environment_provider/environment_provider.py
environment_provider/lib/__init__.py
environment_provider/lib/config.py
environment_provider/lib/database.py
environment_provider/lib/encrypt.py
environment_provider/lib/graphql.py
environment_provider/lib/join.py
environment_provider/lib/json_dumps.py
environment_provider/lib/log_area.py
environment_provider/lib/registry.py
environment_provider/lib/releaser.py
environment_provider/lib/test_suite.py
environment_provider/lib/uuid_generate.py
environment_provider/splitter/__init__.py
environment_provider/splitter/split.py
etos_environment_provider-5.3.5.dist-info/licenses/AUTHORS.rst
etos_environment_provider-5.3.5.dist-info/licenses/LICENSE.txt
execution_space_provider/__init__.py
execution_space_provider/exceptions.py
execution_space_provider/execution_space.py
execution_space_provider/execution_space_provider.py
execution_space_provider/schemas/external_schema.json
execution_space_provider/schemas/jsontas_schema.json
execution_space_provider/utilities/__init__.py
execution_space_provider/utilities/checkin.py
execution_space_provider/utilities/checkout.py
execution_space_provider/utilities/external_provider.py
execution_space_provider/utilities/instructions.py
execution_space_provider/utilities/jsontas_provider.py
execution_space_provider/utilities/list.py
iut_provider/__init__.py
iut_provider/exceptions.py
iut_provider/iut.py
iut_provider/iut_provider.py
iut_provider/schemas/external_schema.json
iut_provider/schemas/jsontas_schema.json
iut_provider/utilities/__init__.py
iut_provider/utilities/checkin.py
iut_provider/utilities/checkout.py
iut_provider/utilities/external_provider.py
iut_provider/utilities/jsontas_provider.py
iut_provider/utilities/list.py
iut_provider/utilities/prepare.py
log_area_provider/__init__.py
log_area_provider/exceptions.py
log_area_provider/log_area.py
log_area_provider/log_area_provider.py
log_area_provider/schemas/external_schema.json
log_area_provider/schemas/jsontas_schema.json
log_area_provider/utilities/__init__.py
etos_environment_provider-5.3.5.dist-info/METADATA
etos_environment_provider-5.3.5.dist-info/WHEEL
etos_environment_provider-5.3.5.dist-info/top_level.txt
etos_environment_provider-5.3.5.dist-info/RECORD
