Metadata-Version: 2.4
Name: etos_environment_provider
Version: 5.3.5
Summary: Environment Provider for ETOS.
Author-email: Tobias Persson <tobias.persson@axis.com>
License: Apache License, Version 2.0
Project-URL: Documentation, https://etos.readthedocs.io/
Project-URL: Homepage, https://github.com/eiffel-community/etos-environment-provider
Project-URL: Repository, https://github.com/eiffel-community/etos-environment-provider
Classifier: Development Status :: 4 - Beta
Classifier: Programming Language :: Python :: 3
Classifier: License :: OSI Approved :: Apache Software License
Requires-Python: >=3.13
License-File: LICENSE.txt
License-File: AUTHORS.rst
Requires-Dist: cryptography<43.0.0,>=42.0.4
Requires-Dist: jsontas<2.0.0,>=1.4.1
Requires-Dist: packageurl-python~=0.11
Requires-Dist: etcd3gw~=2.3
Requires-Dist: etos-lib==5.1.4
Requires-Dist: opentelemetry-api~=1.21
Requires-Dist: opentelemetry-exporter-otlp~=1.21
Requires-Dist: opentelemetry-sdk~=1.21
Provides-Extra: testing
Requires-Dist: pytest; extra == "testing"
Requires-Dist: pytest-cov; extra == "testing"
Dynamic: license-file
